{"note":"This file is an internal implementation detail to speed up HTML report generation. Its format can change at any time. You might be looking for the JSON report: https://coverage.rtfd.io/cmd.html#cmd-json","format":5,"version":"7.9.1","globals":"5d4b015ae800908c076209c3427fabb9","files":{"z_3ff5bfad80aa4e23___git___py":{"hash":"f37dac689deff7a61190f30c31c232cc","index":{"url":"z_3ff5bfad80aa4e23___git___py.html","file":"PyFHD/__git__.py","description":"","nums":{"precision":0,"n_files":1,"n_statements":3,"n_excluded":0,"n_missing":0,"n_branches":0,"n_partial_branches":0,"n_missing_branches":0}}},"z_3ff5bfad80aa4e23___init___py":{"hash":"ca2411bb2d5283cba14da3ce60f5feec","index":{"url":"z_3ff5bfad80aa4e23___init___py.html","file":"PyFHD/__init__.py","description":"","nums":{"precision":0,"n_files":1,"n_statements":0,"n_excluded":0,"n_missing":0,"n_branches":0,"n_partial_branches":0,"n_missing_branches":0}}},"z_baeb8f84a67595ba___init___py":{"hash":"ca2411bb2d5283cba14da3ce60f5feec","index":{"url":"z_baeb8f84a67595ba___init___py.html","file":"PyFHD/beam_setup/__init__.py","description":"","nums":{"precision":0,"n_files":1,"n_statements":0,"n_excluded":0,"n_missing":0,"n_branches":0,"n_partial_branches":0,"n_missing_branches":0}}},"z_baeb8f84a67595ba_antenna_py":{"hash":"427bf67420705f858677b8d347504468","index":{"url":"z_baeb8f84a67595ba_antenna_py.html","file":"PyFHD/beam_setup/antenna.py","description":"","nums":{"precision":0,"n_files":1,"n_statements":133,"n_excluded":0,"n_missing":133,"n_branches":40,"n_partial_branches":0,"n_missing_branches":40}}},"z_baeb8f84a67595ba_beam_py":{"hash":"b286ca166e4c17b9eefdd8d7bf448113","index":{"url":"z_baeb8f84a67595ba_beam_py.html","file":"PyFHD/beam_setup/beam.py","description":"","nums":{"precision":0,"n_files":1,"n_statements":120,"n_excluded":0,"n_missing":120,"n_branches":28,"n_partial_branches":0,"n_missing_branches":28}}},"z_baeb8f84a67595ba_beam_utils_py":{"hash":"91b4a0a3094108fa9d7c742ff8bc9754","index":{"url":"z_baeb8f84a67595ba_beam_utils_py.html","file":"PyFHD/beam_setup/beam_utils.py","description":"","nums":{"precision":0,"n_files":1,"n_statements":166,"n_excluded":0,"n_missing":63,"n_branches":52,"n_partial_branches":13,"n_missing_branches":25}}},"z_baeb8f84a67595ba_mwa_py":{"hash":"37652bf688d329cc97c0d101d81b3487","index":{"url":"z_baeb8f84a67595ba_mwa_py.html","file":"PyFHD/beam_setup/mwa.py","description":"","nums":{"precision":0,"n_files":1,"n_statements":40,"n_excluded":0,"n_missing":40,"n_branches":10,"n_partial_branches":0,"n_missing_branches":10}}},"z_828fdda5354789e6___init___py":{"hash":"ca2411bb2d5283cba14da3ce60f5feec","index":{"url":"z_828fdda5354789e6___init___py.html","file":"PyFHD/calibration/__init__.py","description":"","nums":{"precision":0,"n_files":1,"n_statements":0,"n_excluded":0,"n_missing":0,"n_branches":0,"n_partial_branches":0,"n_missing_branches":0}}},"z_828fdda5354789e6_calibrate_py":{"hash":"0477609903b9e47d412baf5b07d27ed0","index":{"url":"z_828fdda5354789e6_calibrate_py.html","file":"PyFHD/calibration/calibrate.py","description":"","nums":{"precision":0,"n_files":1,"n_statements":107,"n_excluded":0,"n_missing":73,"n_branches":30,"n_partial_branches":0,"n_missing_branches":30}}},"z_828fdda5354789e6_calibration_utils_py":{"hash":"bae535997aca6169b9246b590540bce6","index":{"url":"z_828fdda5354789e6_calibration_utils_py.html","file":"PyFHD/calibration/calibration_utils.py","description":"","nums":{"precision":0,"n_files":1,"n_statements":655,"n_excluded":0,"n_missing":226,"n_branches":252,"n_partial_branches":35,"n_missing_branches":123}}},"z_828fdda5354789e6_vis_calibrate_subroutine_py":{"hash":"52a3334db26f35cc87631eb4de882a6c","index":{"url":"z_828fdda5354789e6_vis_calibrate_subroutine_py.html","file":"PyFHD/calibration/vis_calibrate_subroutine.py","description":"","nums":{"precision":0,"n_files":1,"n_statements":234,"n_excluded":0,"n_missing":19,"n_branches":76,"n_partial_branches":15,"n_missing_branches":15}}},"z_febde04d5a3d7f98___init___py":{"hash":"ca2411bb2d5283cba14da3ce60f5feec","index":{"url":"z_febde04d5a3d7f98___init___py.html","file":"PyFHD/data_setup/__init__.py","description":"","nums":{"precision":0,"n_files":1,"n_statements":0,"n_excluded":0,"n_missing":0,"n_branches":0,"n_partial_branches":0,"n_missing_branches":0}}},"z_febde04d5a3d7f98_obs_py":{"hash":"b1527afd84f055871d68ecfdf8fc6744","index":{"url":"z_febde04d5a3d7f98_obs_py.html","file":"PyFHD/data_setup/obs.py","description":"","nums":{"precision":0,"n_files":1,"n_statements":268,"n_excluded":0,"n_missing":61,"n_branches":76,"n_partial_branches":21,"n_missing_branches":37}}},"z_febde04d5a3d7f98_uvfits_py":{"hash":"aaab5aee6aa7b2c05d5c9a9691cf0f94","index":{"url":"z_febde04d5a3d7f98_uvfits_py.html","file":"PyFHD/data_setup/uvfits.py","description":"","nums":{"precision":0,"n_files":1,"n_statements":303,"n_excluded":0,"n_missing":96,"n_branches":50,"n_partial_branches":15,"n_missing_branches":21}}},"z_41098e5bea5b68aa___init___py":{"hash":"ca2411bb2d5283cba14da3ce60f5feec","index":{"url":"z_41098e5bea5b68aa___init___py.html","file":"PyFHD/flagging/__init__.py","description":"","nums":{"precision":0,"n_files":1,"n_statements":0,"n_excluded":0,"n_missing":0,"n_branches":0,"n_partial_branches":0,"n_missing_branches":0}}},"z_41098e5bea5b68aa_flagging_py":{"hash":"61f751dd8250900f9d873e50f28f17ef","index":{"url":"z_41098e5bea5b68aa_flagging_py.html","file":"PyFHD/flagging/flagging.py","description":"","nums":{"precision":0,"n_files":1,"n_statements":194,"n_excluded":0,"n_missing":63,"n_branches":96,"n_partial_branches":21,"n_missing_branches":53}}},"z_e603c322312734f2___init___py":{"hash":"ca2411bb2d5283cba14da3ce60f5feec","index":{"url":"z_e603c322312734f2___init___py.html","file":"PyFHD/gridding/__init__.py","description":"","nums":{"precision":0,"n_files":1,"n_statements":0,"n_excluded":0,"n_missing":0,"n_branches":0,"n_partial_branches":0,"n_missing_branches":0}}},"z_e603c322312734f2_filters_py":{"hash":"55205f04f8e417fc891b7f43ab6f11bf","index":{"url":"z_e603c322312734f2_filters_py.html","file":"PyFHD/gridding/filters.py","description":"","nums":{"precision":0,"n_files":1,"n_statements":22,"n_excluded":0,"n_missing":4,"n_branches":12,"n_partial_branches":4,"n_missing_branches":4}}},"z_e603c322312734f2_gridding_utils_py":{"hash":"9a0c0b5c510c52c12d7e307f98515837","index":{"url":"z_e603c322312734f2_gridding_utils_py.html","file":"PyFHD/gridding/gridding_utils.py","description":"","nums":{"precision":0,"n_files":1,"n_statements":293,"n_excluded":0,"n_missing":61,"n_branches":108,"n_partial_branches":14,"n_missing_branches":36}}},"z_e603c322312734f2_visibility_degrid_py":{"hash":"536a692b59b385af63523dc8170ee3b9","index":{"url":"z_e603c322312734f2_visibility_degrid_py.html","file":"PyFHD/gridding/visibility_degrid.py","description":"","nums":{"precision":0,"n_files":1,"n_statements":176,"n_excluded":0,"n_missing":169,"n_branches":64,"n_partial_branches":0,"n_missing_branches":64}}},"z_e603c322312734f2_visibility_grid_py":{"hash":"690b691058720794a3227d1dc78c4384","index":{"url":"z_e603c322312734f2_visibility_grid_py.html","file":"PyFHD/gridding/visibility_grid.py","description":"","nums":{"precision":0,"n_files":1,"n_statements":250,"n_excluded":0,"n_missing":13,"n_branches":112,"n_partial_branches":17,"n_missing_branches":17}}},"z_d8066d77adfc45e6___init___py":{"hash":"ca2411bb2d5283cba14da3ce60f5feec","index":{"url":"z_d8066d77adfc45e6___init___py.html","file":"PyFHD/healpix/__init__.py","description":"","nums":{"precision":0,"n_files":1,"n_statements":0,"n_excluded":0,"n_missing":0,"n_branches":0,"n_partial_branches":0,"n_missing_branches":0}}},"z_d8066d77adfc45e6_export_py":{"hash":"daf45651407e4777e9029c85f77b7b57","index":{"url":"z_d8066d77adfc45e6_export_py.html","file":"PyFHD/healpix/export.py","description":"","nums":{"precision":0,"n_files":1,"n_statements":86,"n_excluded":0,"n_missing":86,"n_branches":34,"n_partial_branches":0,"n_missing_branches":34}}},"z_d8066d77adfc45e6_healpix_utils_py":{"hash":"e991a967a630586566f7f8b242ab23ed","index":{"url":"z_d8066d77adfc45e6_healpix_utils_py.html","file":"PyFHD/healpix/healpix_utils.py","description":"","nums":{"precision":0,"n_files":1,"n_statements":247,"n_excluded":0,"n_missing":97,"n_branches":74,"n_partial_branches":16,"n_missing_branches":38}}},"z_694c6539f1290e86___init___py":{"hash":"ca2411bb2d5283cba14da3ce60f5feec","index":{"url":"z_694c6539f1290e86___init___py.html","file":"PyFHD/io/__init__.py","description":"","nums":{"precision":0,"n_files":1,"n_statements":0,"n_excluded":0,"n_missing":0,"n_branches":0,"n_partial_branches":0,"n_missing_branches":0}}},"z_694c6539f1290e86_pyfhd_io_py":{"hash":"0c8d607fb4d6883b221332f744a0d479","index":{"url":"z_694c6539f1290e86_pyfhd_io_py.html","file":"PyFHD/io/pyfhd_io.py","description":"","nums":{"precision":0,"n_files":1,"n_statements":203,"n_excluded":0,"n_missing":50,"n_branches":120,"n_partial_branches":15,"n_missing_branches":35}}},"z_694c6539f1290e86_pyfhd_quickview_py":{"hash":"466e6bdc87ed9b0099154a67e44d50ac","index":{"url":"z_694c6539f1290e86_pyfhd_quickview_py.html","file":"PyFHD/io/pyfhd_quickview.py","description":"","nums":{"precision":0,"n_files":1,"n_statements":177,"n_excluded":0,"n_missing":40,"n_branches":32,"n_partial_branches":9,"n_missing_branches":11}}},"z_449038fa3ad179d9___init___py":{"hash":"ca2411bb2d5283cba14da3ce60f5feec","index":{"url":"z_449038fa3ad179d9___init___py.html","file":"PyFHD/plotting/__init__.py","description":"","nums":{"precision":0,"n_files":1,"n_statements":0,"n_excluded":0,"n_missing":0,"n_branches":0,"n_partial_branches":0,"n_missing_branches":0}}},"z_449038fa3ad179d9_calibration_py":{"hash":"2c1a8503458081176be9aa140ce3b6b6","index":{"url":"z_449038fa3ad179d9_calibration_py.html","file":"PyFHD/plotting/calibration.py","description":"","nums":{"precision":0,"n_files":1,"n_statements":95,"n_excluded":0,"n_missing":88,"n_branches":32,"n_partial_branches":0,"n_missing_branches":32}}},"z_449038fa3ad179d9_gridding_py":{"hash":"7355248c81cf530e6967ee48ad1a2e19","index":{"url":"z_449038fa3ad179d9_gridding_py.html","file":"PyFHD/plotting/gridding.py","description":"","nums":{"precision":0,"n_files":1,"n_statements":27,"n_excluded":0,"n_missing":27,"n_branches":8,"n_partial_branches":0,"n_missing_branches":8}}},"z_449038fa3ad179d9_image_py":{"hash":"7d0f765ed3ef6110b477bc9c379cbe46","index":{"url":"z_449038fa3ad179d9_image_py.html","file":"PyFHD/plotting/image.py","description":"","nums":{"precision":0,"n_files":1,"n_statements":304,"n_excluded":0,"n_missing":291,"n_branches":182,"n_partial_branches":0,"n_missing_branches":182}}},"z_3ff5bfad80aa4e23_pyfhd_py":{"hash":"e77d68bd2da58fb0cf0d62074f1a6758","index":{"url":"z_3ff5bfad80aa4e23_pyfhd_py.html","file":"PyFHD/pyfhd.py","description":"","nums":{"precision":0,"n_files":1,"n_statements":293,"n_excluded":0,"n_missing":293,"n_branches":108,"n_partial_branches":0,"n_missing_branches":108}}},"z_8736c67581728844___init___py":{"hash":"ca2411bb2d5283cba14da3ce60f5feec","index":{"url":"z_8736c67581728844___init___py.html","file":"PyFHD/pyfhd_tools/__init__.py","description":"","nums":{"precision":0,"n_files":1,"n_statements":0,"n_excluded":0,"n_missing":0,"n_branches":0,"n_partial_branches":0,"n_missing_branches":0}}},"z_8736c67581728844_pyfhd_setup_py":{"hash":"bd8613820d4a3fe5b789992d39adf395","index":{"url":"z_8736c67581728844_pyfhd_setup_py.html","file":"PyFHD/pyfhd_tools/pyfhd_setup.py","description":"","nums":{"precision":0,"n_files":1,"n_statements":337,"n_excluded":0,"n_missing":86,"n_branches":94,"n_partial_branches":32,"n_missing_branches":46}}},"z_8736c67581728844_pyfhd_utils_py":{"hash":"2427ea264fa33c479d8a8a931a9a3573","index":{"url":"z_8736c67581728844_pyfhd_utils_py.html","file":"PyFHD/pyfhd_tools/pyfhd_utils.py","description":"","nums":{"precision":0,"n_files":1,"n_statements":475,"n_excluded":0,"n_missing":85,"n_branches":212,"n_partial_branches":35,"n_missing_branches":63}}},"z_8736c67581728844_test_utils_py":{"hash":"642bbcb60e90b4c3ac6bead36c1f943a","index":{"url":"z_8736c67581728844_test_utils_py.html","file":"PyFHD/pyfhd_tools/test_utils.py","description":"","nums":{"precision":0,"n_files":1,"n_statements":94,"n_excluded":0,"n_missing":34,"n_branches":40,"n_partial_branches":4,"n_missing_branches":24}}},"z_8736c67581728844_unit_conv_py":{"hash":"67dcd332b0ca6594ab9346d35863eb46","index":{"url":"z_8736c67581728844_unit_conv_py.html","file":"PyFHD/pyfhd_tools/unit_conv.py","description":"","nums":{"precision":0,"n_files":1,"n_statements":44,"n_excluded":0,"n_missing":0,"n_branches":2,"n_partial_branches":0,"n_missing_branches":0}}},"z_2f5d8eaf593f2b51___init___py":{"hash":"ca2411bb2d5283cba14da3ce60f5feec","index":{"url":"z_2f5d8eaf593f2b51___init___py.html","file":"PyFHD/source_modeling/__init__.py","description":"","nums":{"precision":0,"n_files":1,"n_statements":0,"n_excluded":0,"n_missing":0,"n_branches":0,"n_partial_branches":0,"n_missing_branches":0}}},"z_2f5d8eaf593f2b51_vis_model_transfer_py":{"hash":"16289098b927960c5af9ab7e6dc5227b","index":{"url":"z_2f5d8eaf593f2b51_vis_model_transfer_py.html","file":"PyFHD/source_modeling/vis_model_transfer.py","description":"","nums":{"precision":0,"n_files":1,"n_statements":158,"n_excluded":0,"n_missing":43,"n_branches":60,"n_partial_branches":13,"n_missing_branches":25}}},"z_47dcd11ecdd8e2d6___init___py":{"hash":"8f96e0487d400bed7b4c91e861310773","index":{"url":"z_47dcd11ecdd8e2d6___init___py.html","file":"PyFHD/templates/__init__.py","description":"","nums":{"precision":0,"n_files":1,"n_statements":0,"n_excluded":0,"n_missing":0,"n_branches":0,"n_partial_branches":0,"n_missing_branches":0}}}}}